redis_init_zero/__init__.py
redis_init_zero-2025.9.13174.dist-info/licenses/LICENSE
redis_init_zero-2025.9.13174.dist-info/METADATA
redis_init_zero-2025.9.13174.dist-info/WHEEL
redis_init_zero-2025.9.13174.dist-info/top_level.txt
redis_init_zero-2025.9.13174.dist-info/RECORD
