Metadata-Version: 2.4
Name: redis_init_zero
Version: 2025.9.13174
Summary: a function that recieve the key and redis connection string and then: 1. check if key doesnt exist then to create this key with value 0 2. …
Author-email: Eugene Evstafev <hi@eugene.plus>
License: MIT License
Project-URL: Repository, https://pypi.org/project/redis_init_zero/
Requires-Python: >=3.9
License-File: LICENSE
Requires-Dist: redis
Dynamic: license-file
